README.rst
setup.py
minipot/__init__.py
minipot/__main__.py
minipot/shell_simulator.py
minipot.egg-info/PKG-INFO
minipot.egg-info/SOURCES.txt
minipot.egg-info/dependency_links.txt
minipot.egg-info/not-zip-safe
minipot.egg-info/top_level.txt