Metadata-Version: 1.0
Name: minipot
Version: 1.0.0.0
Summary: A simple honey pot for reverse tcp shell attacks, netcat reverse shell attacks ...
Home-page: UNKNOWN
Author: msris108
Author-email: msris108@gmail.com
License: MIT
Platform: UNKNOWN
